{"text":"Счеть\nКракова.\nMARRIAGES\nAISTPILI§CKSÅ HUITI A\n2011\nМокстопроисхожденіе, имя, фамилі» Имена отца Мксторожденіє, имя, фамилію. Имена отца\nМесяца и вѣроисповѣданіє жениха, сколько\nН ДЕНЬ.\nлетя отъ роду и которымя\nБраком.\nNUMBER\nDATE\nFULL NAME OF GROOM, RESIDENCE,\nAGE, RELIGION, 1st or 2nd MARRIAGE\nи вероисповедание невесты,\nИ\nH\nсколько лет отъ роду и\nкоторым\nбракомъ.\nΑΙ ΑΤΕΛΗ,\nMATEOH.\nFIRST NAMES\nJuly 10 Scott Joseph Nagele\nWashington Township N.J.\n24\nFULL NAME OF BRIDE, RESIDENCE.\nFIRST NAMES\nOF GROOM'S AGE, RELIGION, 1st or 2nd MARRIAGE OF BRIDE'S\nPARENTS\nPARENTS\nRobert\nAmeruda Savch\nRobert\nKathleen\nManville, N.J\nstray\n34\nOrthodox\nRoman Catholic\nYEAR\nH\nMM, CTL FTSFAN, ( GPESCS4CTAHUNGE\nKTO COREOшAAZ\nтаинство.\nPRIEST'S NAME\nКто были поручители.\nWITNESSES NAMES\nОтя какого числа и за какимя\n№ License.\nFor Jas\nParell\nEric Nagele\nKatherine markerich\nDATE AND NUMBER OF LICENSE\n6-28-2011\nMC 29-2011\n2\nJuly 17 Christopher Michel Brooks\nRonald\nCatherine Gorbztuk Peter\nNo. Brunswick, NJ\nSuszy\nC2101\nManville, NJ.\nFr.\nPards\nда\n25\nRoman Catholic\n25\nTimothy Gorbetun\nRebeca Gorbitay\n7-08-2011\n11-134","pages":[{"pageIndex":0,"width":4160,"height":3120,"blocks":[{"blockType":"TEXT","confidence":0.6851555705070496,"boundingBox":{"vertices":[{"x":167,"y":410},{"x":289,"y":419},{"x":286,"y":455},{"x":164,"y":446}],"normalizedVertices":[]},"paragraphs":[{"confidence":0.6851555705070496,"boundingBox":{"vertices":[{"x":167,"y":410},{"x":289,"y":419},{"x":286,"y":455},{"x":164,"y":446}],"normalizedVertices":[]},"words":[{"text":"Счеть","confidence":0.6851555705070496,"boundingBox":{"vertices":[{"x":167,"y":410},{"x":289,"y":419},{"x":286,"y":455},{"x":164,"y":446}],"normalizedVertices":[]}}]}]},{"blockType":"TEXT","confidence":0.8537676930427551,"boundingBox":{"vertices":[{"x":146,"y":518},{"x":304,"y":527},{"x":302,"y":560},{"x":144,"y":551}],"normalizedVertices":[]},"paragraphs":[{"confidence":0.8537676930427551,"boundingBox":{"vertices":[{"x":146,"y":518},{"x":304,"y":527},{"x":302,"y":560},{"x":144,"y":551}],"normalizedVertices":[]},"words":[{"text":"Кракова","confidence":0.8388521671295166,"boundingBox":{"vertices":[{"x":146,"y":518},{"x":295,"y":526},{"x":293,"y":559},{"x":144,"y":551}],"normalizedVertices":[]}},{"text":".","confidence":0.9581763744354248,"boundingBox":{"vertices":[{"x":295,"y":527},{"x":304,"y":528},{"x":302,"y":559},{"x":293,"y":559}],"normalizedVertices":[]}}]}]},{"blockType":"TEXT","confidence":0.9847307205200195,"boundingBox":{"vertices":[{"x":1610,"y":65},{"x":2222,"y":154},{"x":2211,"y":223},{"x":1600,"y":134}],"normalizedVertices":[]},"paragraphs":[{"confidence":0.9847307205200195,"boundingBox":{"vertices":[{"x":1610,"y":65},{"x":2222,"y":154},{"x":2211,"y":223},{"x":1600,"y":134}],"normalizedVertices":[]},"words":[{"text":"MARRIAGES","confidence":0.9847307205200195,"boundingBox":{"vertices":[{"x":1610,"y":65},{"x":2222,"y":154},{"x":2211,"y":223},{"x":1600,"y":134}],"normalizedVertices":[]}}]}]},{"blockType":"TEXT","confidence":0.46641597151756287,"boundingBox":{"vertices":[{"x":1213,"y":180},{"x":1930,"y":261},{"x":1920,"y":355},{"x":1202,"y":273}],"normalizedVertices":[]},"paragraphs":[{"confidence":0.46641597151756287,"boundingBox":{"vertices":[{"x":1213,"y":180},{"x":1930,"y":261},{"x":1920,"y":355},{"x":1202,"y":273}],"normalizedVertices":[]},"words":[{"text":"AISTPILI§CKSÅ","confidence":0.4873143136501312,"boundingBox":{"vertices":[{"x":1213,"y":180},{"x":1619,"y":226},{"x":1609,"y":320},{"x":1202,"y":273}],"normalizedVertices":[]}},{"text":"HUITI","confidence":0.3340933620929718,"boundingBox":{"vertices":[{"x":1660,"y":231},{"x":1822,"y":249},{"x":1811,"y":343},{"x":1649,"y":324}],"normalizedVertices":[]}},{"text":"A","confidence":0.8563504815101624,"boundingBox":{"vertices":[{"x":1871,"y":255},{"x":1931,"y":262},{"x":1920,"y":354},{"x":1861,"y":347}],"normalizedVertices":[]}}]}]},{"blockType":"TEXT","confidence":0.9907073378562927,"boundingBox":{"vertices":[{"x":1933,"y":357},{"x":2070,"y":372},{"x":2063,"y":436},{"x":1926,"y":421}],"normalizedVertices":[]},"paragraphs":[{"confidence":0.9907073378562927,"boundingBox":{"vertices":[{"x":1933,"y":357},{"x":2070,"y":372},{"x":2063,"y":436},{"x":1926,"y":421}],"normalizedVertices":[]},"words":[{"text":"2011","confidence":0.9907073378562927,"boundingBox":{"vertices":[{"x":1933,"y":357},{"x":2070,"y":372},{"x":2063,"y":436},{"x":1926,"y":421}],"normalizedVertices":[]}}]}]},{"blockType":"TEXT","confidence":0.8948472142219543,"boundingBox":{"vertices":[{"x":363,"y":344},{"x":2192,"y":548},{"x":2177,"y":682},{"x":348,"y":478}],"normalizedVertices":[]},"paragraphs":[{"confidence":0.9139701724052429,"boundingBox":{"vertices":[{"x":560,"y":374},{"x":2192,"y":549},{"x":2186,"y":605},{"x":554,"y":431}],"normalizedVertices":[]},"words":[{"text":"Мокстопроисхожденіе","confidence":0.8708293437957764,"boundingBox":{"vertices":[{"x":560,"y":374},{"x":952,"y":416},{"x":946,"y":473},{"x":554,"y":431}],"normalizedVertices":[]}},{"text":",","confidence":0.9708303809165955,"boundingBox":{"vertices":[{"x":951,"y":416},{"x":964,"y":417},{"x":958,"y":473},{"x":945,"y":472}],"normalizedVertices":[]}},{"text":"имя","confidence":0.8054212331771851,"boundingBox":{"vertices":[{"x":966,"y":418},{"x":1053,"y":427},{"x":1047,"y":483},{"x":960,"y":474}],"normalizedVertices":[]}},{"text":",","confidence":0.9330524802207947,"boundingBox":{"vertices":[{"x":1052,"y":427},{"x":1064,"y":428},{"x":1058,"y":484},{"x":1046,"y":483}],"normalizedVertices":[]}},{"text":"фамилі","confidence":0.9708358645439148,"boundingBox":{"vertices":[{"x":1069,"y":429},{"x":1206,"y":444},{"x":1200,"y":499},{"x":1063,"y":485}],"normalizedVertices":[]}},{"text":"»","confidence":0.4733906686306,"boundingBox":{"vertices":[{"x":1200,"y":443},{"x":1231,"y":446},{"x":1225,"y":502},{"x":1194,"y":499}],"normalizedVertices":[]}},{"text":"Имена","confidence":0.9444634318351746,"boundingBox":{"vertices":[{"x":1235,"y":447},{"x":1352,"y":460},{"x":1346,"y":515},{"x":1229,"y":503}],"normalizedVertices":[]}},{"text":"отца","confidence":0.9847168326377869,"boundingBox":{"vertices":[{"x":1358,"y":460},{"x":1446,"y":469},{"x":1441,"y":525},{"x":1352,"y":516}],"normalizedVertices":[]}},{"text":"Мксторожденіє","confidence":0.9199572205543518,"boundingBox":{"vertices":[{"x":1465,"y":471},{"x":1730,"y":499},{"x":1724,"y":556},{"x":1459,"y":528}],"normalizedVertices":[]}},{"text":",","confidence":0.9838056564331055,"boundingBox":{"vertices":[{"x":1733,"y":500},{"x":1743,"y":501},{"x":1737,"y":557},{"x":1727,"y":556}],"normalizedVertices":[]}},{"text":"имя","confidence":0.8503597378730774,"boundingBox":{"vertices":[{"x":1751,"y":502},{"x":1828,"y":510},{"x":1822,"y":566},{"x":1745,"y":558}],"normalizedVertices":[]}},{"text":",","confidence":0.9692147374153137,"boundingBox":{"vertices":[{"x":1828,"y":510},{"x":1838,"y":511},{"x":1832,"y":567},{"x":1822,"y":566}],"normalizedVertices":[]}},{"text":"фамилію","confidence":0.9408769011497498,"boundingBox":{"vertices":[{"x":1851,"y":512},{"x":1992,"y":527},{"x":1986,"y":584},{"x":1845,"y":569}],"normalizedVertices":[]}},{"text":".","confidence":0.7226496338844299,"boundingBox":{"vertices":[{"x":1971,"y":525},{"x":1998,"y":528},{"x":1992,"y":584},{"x":1965,"y":581}],"normalizedVertices":[]}},{"text":"Имена","confidence":0.994850754737854,"boundingBox":{"vertices":[{"x":2015,"y":530},{"x":2116,"y":541},{"x":2110,"y":597},{"x":2009,"y":586}],"normalizedVertices":[]}},{"text":"отца","confidence":0.9939211010932922,"boundingBox":{"vertices":[{"x":2124,"y":541},{"x":2192,"y":548},{"x":2186,"y":605},{"x":2118,"y":598}],"normalizedVertices":[]}}]},{"confidence":0.8550076484680176,"boundingBox":{"vertices":[{"x":355,"y":420},{"x":1208,"y":519},{"x":1202,"y":573},{"x":349,"y":474}],"normalizedVertices":[]},"words":[{"text":"Месяца","confidence":0.4052368402481079,"boundingBox":{"vertices":[{"x":355,"y":420},{"x":534,"y":441},{"x":528,"y":494},{"x":349,"y":474}],"normalizedVertices":[]}},{"text":"и","confidence":0.7653585076332092,"boundingBox":{"vertices":[{"x":567,"y":445},{"x":591,"y":448},{"x":585,"y":500},{"x":561,"y":498}],"normalizedVertices":[]}},{"text":"вѣроисповѣданіє","confidence":0.910822331905365,"boundingBox":{"vertices":[{"x":602,"y":449},{"x":919,"y":486},{"x":913,"y":540},{"x":596,"y":503}],"normalizedVertices":[]}},{"text":"жениха","confidence":0.9911120533943176,"boundingBox":{"vertices":[{"x":927,"y":487},{"x":1056,"y":502},{"x":1050,"y":556},{"x":921,"y":541}],"normalizedVertices":[]}},{"text":",","confidence":0.9946354031562805,"boundingBox":{"vertices":[{"x":1057,"y":502},{"x":1067,"y":503},{"x":1061,"y":556},{"x":1051,"y":555}],"normalizedVertices":[]}},{"text":"сколько","confidence":0.9971218109130859,"boundingBox":{"vertices":[{"x":1076,"y":504},{"x":1208,"y":519},{"x":1202,"y":573},{"x":1070,"y":558}],"normalizedVertices":[]}}]}]},{"blockType":"TEXT","confidence":0.649950385093689,"boundingBox":{"vertices":[{"x":359,"y":533},{"x":505,"y":547},{"x":503,"y":577},{"x":356,"y":563}],"normalizedVertices":[]},"paragraphs":[{"confidence":0.649950385093689,"boundingBox":{"vertices":[{"x":359,"y":533},{"x":505,"y":547},{"x":503,"y":577},{"x":356,"y":563}],"normalizedVertices":[]},"words":[{"text":"Н","confidence":0.4523807466030121,"boundingBox":{"vertices":[{"x":359,"y":534},{"x":384,"y":536},{"x":381,"y":565},{"x":356,"y":563}],"normalizedVertices":[]}},{"text":"ДЕНЬ","confidence":0.6436881422996521,"boundingBox":{"vertices":[{"x":408,"y":538},{"x":497,"y":546},{"x":494,"y":576},{"x":405,"y":568}],"normalizedVertices":[]}},{"text":".","confidence":0.8725690841674805,"boundingBox":{"vertices":[{"x":495,"y":546},{"x":505,"y":547},{"x":502,"y":576},{"x":492,"y":575}],"normalizedVertices":[]}}]}]},{"blockType":"TEXT","confidence":0.9216399788856506,"boundingBox":{"vertices":[{"x":607,"y":544},{"x":1172,"y":589},{"x":1164,"y":698},{"x":598,"y":654}],"normalizedVertices":[]},"paragraphs":[{"confidence":0.9216399788856506,"boundingBox":{"vertices":[{"x":607,"y":544},{"x":1172,"y":589},{"x":1164,"y":698},{"x":598,"y":654}],"normalizedVertices":[]},"words":[{"text":"летя","confidence":0.7057366967201233,"boundingBox":{"vertices":[{"x":607,"y":544},{"x":711,"y":554},{"x":708,"y":586},{"x":604,"y":576}],"normalizedVertices":[]}},{"text":"отъ","confidence":0.9602152109146118,"boundingBox":{"vertices":[{"x":735,"y":556},{"x":804,"y":562},{"x":801,"y":594},{"x":732,"y":588}],"normalizedVertices":[]}},{"text":"роду","confidence":0.9520204663276672,"boundingBox":{"vertices":[{"x":828,"y":565},{"x":913,"y":573},{"x":910,"y":604},{"x":825,"y":596}],"normalizedVertices":[]}},{"text":"и","confidence":0.964038074016571,"boundingBox":{"vertices":[{"x":936,"y":575},{"x":960,"y":577},{"x":957,"y":608},{"x":933,"y":606}],"normalizedVertices":[]}},{"text":"которымя","confidence":0.9520891904830933,"boundingBox":{"vertices":[{"x":985,"y":580},{"x":1171,"y":598},{"x":1168,"y":628},{"x":982,"y":611}],"normalizedVertices":[]}},{"text":"Браком","confidence":0.9763656854629517,"boundingBox":{"vertices":[{"x":807,"y":638},{"x":935,"y":646},{"x":933,"y":678},{"x":805,"y":670}],"normalizedVertices":[]}},{"text":".","confidence":0.9336590766906738,"boundingBox":{"vertices":[{"x":962,"y":648},{"x":970,"y":649},{"x":968,"y":679},{"x":960,"y":679}],"normalizedVertices":[]}}]}]},{"blockType":"TEXT","confidence":0.987233579158783,"boundingBox":{"vertices":[{"x":144,"y":719},{"x":270,"y":726},{"x":269,"y":748},{"x":143,"y":742}],"normalizedVertices":[]},"paragraphs":[{"confidence":0.987233579158783,"boundingBox":{"vertices":[{"x":144,"y":719},{"x":270,"y":726},{"x":269,"y":748},{"x":143,"y":742}],"normalizedVertices":[]},"words":[{"text":"NUMBER","confidence":0.987233579158783,"boundingBox":{"vertices":[{"x":144,"y":719},{"x":270,"y":726},{"x":269,"y":748},{"x":143,"y":742}],"normalizedVertices":[]}}]}]},{"blockType":"TEXT","confidence":0.9913486242294312,"boundingBox":{"vertices":[{"x":394,"y":736},{"x":478,"y":742},{"x":476,"y":764},{"x":392,"y":758}],"normalizedVertices":[]},"paragraphs":[{"confidence":0.9913486242294312,"boundingBox":{"vertices":[{"x":394,"y":736},{"x":478,"y":742},{"x":476,"y":764},{"x":392,"y":758}],"normalizedVertices":[]},"words":[{"text":"DATE","confidence":0.9913486242294312,"boundingBox":{"vertices":[{"x":394,"y":736},{"x":478,"y":742},{"x":476,"y":764},{"x":392,"y":758}],"normalizedVertices":[]}}]}]},{"blockType":"TEXT","confidence":0.9676280617713928,"boundingBox":{"vertices":[{"x":579,"y":729},{"x":1196,"y":775},{"x":1191,"y":853},{"x":573,"y":807}],"normalizedVertices":[]},"paragraphs":[{"confidence":0.9676280617713928,"boundingBox":{"vertices":[{"x":579,"y":729},{"x":1196,"y":775},{"x":1191,"y":853},{"x":573,"y":807}],"normalizedVertices":[]},"words":[{"text":"FULL","confidence":0.9897961020469666,"boundingBox":{"vertices":[{"x":579,"y":729},{"x":661,"y":735},{"x":658,"y":765},{"x":577,"y":759}],"normalizedVertices":[]}},{"text":"NAME","confidence":0.9901460409164429,"boundingBox":{"vertices":[{"x":685,"y":737},{"x":768,"y":743},{"x":765,"y":773},{"x":683,"y":767}],"normalizedVertices":[]}},{"text":"OF","confidence":0.9853438138961792,"boundingBox":{"vertices":[{"x":791,"y":745},{"x":830,"y":748},{"x":828,"y":778},{"x":789,"y":775}],"normalizedVertices":[]}},{"text":"GROOM","confidence":0.9700487852096558,"boundingBox":{"vertices":[{"x":854,"y":750},{"x":954,"y":758},{"x":951,"y":787},{"x":852,"y":780}],"normalizedVertices":[]}},{"text":",","confidence":0.7267394661903381,"boundingBox":{"vertices":[{"x":958,"y":758},{"x":966,"y":759},{"x":964,"y":788},{"x":956,"y":787}],"normalizedVertices":[]}},{"text":"RESIDENCE","confidence":0.9650430083274841,"boundingBox":{"vertices":[{"x":996,"y":761},{"x":1173,"y":774},{"x":1171,"y":803},{"x":994,"y":790}],"normalizedVertices":[]}},{"text":",","confidence":0.7496010661125183,"boundingBox":{"vertices":[{"x":1178,"y":775},{"x":1189,"y":776},{"x":1187,"y":805},{"x":1176,"y":804}],"normalizedVertices":[]}},{"text":"AGE","confidence":0.9885737895965576,"boundingBox":{"vertices":[{"x":579,"y":779},{"x":641,"y":783},{"x":639,"y":811},{"x":577,"y":807}],"normalizedVertices":[]}},{"text":",","confidence":0.9589575529098511,"boundingBox":{"vertices":[{"x":645,"y":784},{"x":653,"y":785},{"x":651,"y":812},{"x":643,"y":811}],"normalizedVertices":[]}},{"text":"RELIGION","confidence":0.9860638380050659,"boundingBox":{"vertices":[{"x":664,"y":785},{"x":829,"y":797},{"x":827,"y":825},{"x":662,"y":813}],"normalizedVertices":[]}},{"text":",","confidence":0.9496728181838989,"boundingBox":{"vertices":[{"x":833,"y":798},{"x":843,"y":799},{"x":841,"y":826},{"x":831,"y":825}],"normalizedVertices":[]}},{"text":"1st","confidence":0.917351245880127,"boundingBox":{"vertices":[{"x":858,"y":799},{"x":912,"y":803},{"x":910,"y":831},{"x":856,"y":827}],"normalizedVertices":[]}},{"text":"or","confidence":0.9659304022789001,"boundingBox":{"vertices":[{"x":928,"y":804},{"x":965,"y":807},{"x":963,"y":835},{"x":926,"y":832}],"normalizedVertices":[]}},{"text":"2nd","confidence":0.9899841547012329,"boundingBox":{"vertices":[{"x":979,"y":809},{"x":1026,"y":812},{"x":1024,"y":839},{"x":977,"y":836}],"normalizedVertices":[]}},{"text":"MARRIAGE","confidence":0.9875484108924866,"boundingBox":{"vertices":[{"x":1034,"y":812},{"x":1193,"y":824},{"x":1191,"y":851},{"x":1032,"y":840}],"normalizedVertices":[]}}]}]},{"blockType":"TEXT","confidence":0.8665233850479126,"boundingBox":{"vertices":[{"x":1487,"y":547},{"x":1976,"y":586},{"x":1973,"y":628},{"x":1484,"y":589}],"normalizedVertices":[]},"paragraphs":[{"confidence":0.8665233850479126,"boundingBox":{"vertices":[{"x":1487,"y":547},{"x":1976,"y":586},{"x":1973,"y":628},{"x":1484,"y":589}],"normalizedVertices":[]},"words":[{"text":"и","confidence":0.8708160519599915,"boundingBox":{"vertices":[{"x":1487,"y":548},{"x":1512,"y":550},{"x":1509,"y":591},{"x":1484,"y":589}],"normalizedVertices":[]}},{"text":"вероисповедание","confidence":0.863605797290802,"boundingBox":{"vertices":[{"x":1529,"y":550},{"x":1809,"y":572},{"x":1806,"y":614},{"x":1526,"y":592}],"normalizedVertices":[]}},{"text":"невесты","confidence":0.8585996031761169,"boundingBox":{"vertices":[{"x":1827,"y":574},{"x":1967,"y":585},{"x":1963,"y":627},{"x":1824,"y":616}],"normalizedVertices":[]}},{"text":",","confidence":0.9614603519439697,"boundingBox":{"vertices":[{"x":1968,"y":586},{"x":1976,"y":587},{"x":1973,"y":628},{"x":1965,"y":627}],"normalizedVertices":[]}}]}]},{"blockType":"TEXT","confidence":0.9010088443756104,"boundingBox":{"vertices":[{"x":1325,"y":578},{"x":1346,"y":580},{"x":1345,"y":598},{"x":1324,"y":596}],"normalizedVertices":[]},"paragraphs":[{"confidence":0.9010088443756104,"boundingBox":{"vertices":[{"x":1325,"y":578},{"x":1346,"y":580},{"x":1345,"y":598},{"x":1324,"y":596}],"normalizedVertices":[]},"words":[{"text":"И","confidence":0.9010088443756104,"boundingBox":{"vertices":[{"x":1325,"y":578},{"x":1346,"y":580},{"x":1345,"y":598},{"x":1324,"y":596}],"normalizedVertices":[]}}]}]},{"blockType":"TEXT","confidence":0.7934321761131287,"boundingBox":{"vertices":[{"x":2096,"y":648},{"x":2113,"y":650},{"x":2111,"y":668},{"x":2094,"y":666}],"normalizedVertices":[]},"paragraphs":[{"confidence":0.7934321761131287,"boundingBox":{"vertices":[{"x":2096,"y":648},{"x":2113,"y":650},{"x":2111,"y":668},{"x":2094,"y":666}],"normalizedVertices":[]},"words":[{"text":"H","confidence":0.7934321761131287,"boundingBox":{"vertices":[{"x":2096,"y":648},{"x":2113,"y":650},{"x":2111,"y":668},{"x":2094,"y":666}],"normalizedVertices":[]}}]}]},{"blockType":"TEXT","confidence":0.8527504801750183,"boundingBox":{"vertices":[{"x":1504,"y":612},{"x":1960,"y":654},{"x":1957,"y":688},{"x":1501,"y":646}],"normalizedVertices":[]},"paragraphs":[{"confidence":0.8527504801750183,"boundingBox":{"vertices":[{"x":1504,"y":612},{"x":1960,"y":654},{"x":1957,"y":688},{"x":1501,"y":646}],"normalizedVertices":[]},"words":[{"text":"сколько","confidence":0.9865719676017761,"boundingBox":{"vertices":[{"x":1504,"y":612},{"x":1624,"y":623},{"x":1621,"y":657},{"x":1501,"y":646}],"normalizedVertices":[]}},{"text":"лет","confidence":0.7495701909065247,"boundingBox":{"vertices":[{"x":1646,"y":625},{"x":1713,"y":631},{"x":1710,"y":665},{"x":1643,"y":659}],"normalizedVertices":[]}},{"text":"отъ","confidence":0.8829717040061951,"boundingBox":{"vertices":[{"x":1764,"y":637},{"x":1826,"y":643},{"x":1823,"y":676},{"x":1761,"y":670}],"normalizedVertices":[]}},{"text":"роду","confidence":0.6902673244476318,"boundingBox":{"vertices":[{"x":1847,"y":644},{"x":1920,"y":651},{"x":1917,"y":684},{"x":1844,"y":677}],"normalizedVertices":[]}},{"text":"и","confidence":0.784810483455658,"boundingBox":{"vertices":[{"x":1940,"y":653},{"x":1960,"y":655},{"x":1957,"y":688},{"x":1937,"y":686}],"normalizedVertices":[]}}]}]},{"blockType":"TEXT","confidence":0.9767951965332031,"boundingBox":{"vertices":[{"x":1557,"y":687},{"x":1704,"y":697},{"x":1701,"y":727},{"x":1555,"y":717}],"normalizedVertices":[]},"paragraphs":[{"confidence":0.9767951965332031,"boundingBox":{"vertices":[{"x":1557,"y":687},{"x":1704,"y":697},{"x":1701,"y":727},{"x":1555,"y":717}],"normalizedVertices":[]},"words":[{"text":"которым","confidence":0.9767951965332031,"boundingBox":{"vertices":[{"x":1557,"y":687},{"x":1704,"y":697},{"x":1701,"y":727},{"x":1555,"y":717}],"normalizedVertices":[]}}]}]},{"blockType":"TEXT","confidence":0.9156211614608765,"boundingBox":{"vertices":[{"x":1747,"y":701},{"x":1891,"y":711},{"x":1889,"y":740},{"x":1745,"y":730}],"normalizedVertices":[]},"paragraphs":[{"confidence":0.9156211614608765,"boundingBox":{"vertices":[{"x":1747,"y":701},{"x":1891,"y":711},{"x":1889,"y":740},{"x":1745,"y":730}],"normalizedVertices":[]},"words":[{"text":"бракомъ","confidence":0.9136492609977722,"boundingBox":{"vertices":[{"x":1747,"y":701},{"x":1883,"y":711},{"x":1881,"y":740},{"x":1745,"y":730}],"normalizedVertices":[]}},{"text":".","confidence":0.9294243454933167,"boundingBox":{"vertices":[{"x":1883,"y":711},{"x":1891,"y":712},{"x":1889,"y":740},{"x":1881,"y":740}],"normalizedVertices":[]}}]}]},{"blockType":"TEXT","confidence":0.699648380279541,"boundingBox":{"vertices":[{"x":2049,"y":729},{"x":2160,"y":742},{"x":2157,"y":770},{"x":2046,"y":757}],"normalizedVertices":[]},"paragraphs":[{"confidence":0.699648380279541,"boundingBox":{"vertices":[{"x":2049,"y":729},{"x":2160,"y":742},{"x":2157,"y":770},{"x":2046,"y":757}],"normalizedVertices":[]},"words":[{"text":"ΑΙ","confidence":0.2724955379962921,"boundingBox":{"vertices":[{"x":2049,"y":729},{"x":2075,"y":732},{"x":2072,"y":760},{"x":2046,"y":757}],"normalizedVertices":[]}},{"text":"ΑΤΕΛΗ","confidence":0.8521906137466431,"boundingBox":{"vertices":[{"x":2076,"y":732},{"x":2153,"y":741},{"x":2150,"y":769},{"x":2073,"y":760}],"normalizedVertices":[]}},{"text":",","confidence":0.7912428975105286,"boundingBox":{"vertices":[{"x":2154,"y":742},{"x":2160,"y":743},{"x":2157,"y":770},{"x":2151,"y":769}],"normalizedVertices":[]}}]}]},{"blockType":"TEXT","confidence":0.5767306089401245,"boundingBox":{"vertices":[{"x":1271,"y":663},{"x":1406,"y":676},{"x":1404,"y":705},{"x":1268,"y":692}],"normalizedVertices":[]},"paragraphs":[{"confidence":0.5767306089401245,"boundingBox":{"vertices":[{"x":1271,"y":663},{"x":1406,"y":676},{"x":1404,"y":705},{"x":1268,"y":692}],"normalizedVertices":[]},"words":[{"text":"MATEOH","confidence":0.5640413761138916,"boundingBox":{"vertices":[{"x":1271,"y":663},{"x":1388,"y":674},{"x":1386,"y":703},{"x":1268,"y":692}],"normalizedVertices":[]}},{"text":".","confidence":0.6528660655021667,"boundingBox":{"vertices":[{"x":1393,"y":675},{"x":1406,"y":676},{"x":1403,"y":704},{"x":1390,"y":703}],"normalizedVertices":[]}}]}]},{"blockType":"TEXT","confidence":0.9825131893157959,"boundingBox":{"vertices":[{"x":1228,"y":776},{"x":1437,"y":791},{"x":1436,"y":819},{"x":1226,"y":804}],"normalizedVertices":[]},"paragraphs":[{"confidence":0.9825131893157959,"boundingBox":{"vertices":[{"x":1228,"y":776},{"x":1437,"y":791},{"x":1436,"y":819},{"x":1226,"y":804}],"normalizedVertices":[]},"words":[{"text":"FIRST","confidence":0.9829461574554443,"boundingBox":{"vertices":[{"x":1228,"y":776},{"x":1323,"y":783},{"x":1321,"y":811},{"x":1226,"y":804}],"normalizedVertices":[]}},{"text":"NAMES","confidence":0.9820801615715027,"boundingBox":{"vertices":[{"x":1343,"y":784},{"x":1438,"y":791},{"x":1436,"y":819},{"x":1341,"y":812}],"normalizedVertices":[]}}]}]},{"blockType":"TEXT","confidence":0.8521816730499268,"boundingBox":{"vertices":[{"x":329,"y":897},{"x":1193,"y":909},{"x":1190,"y":1124},{"x":326,"y":1112}],"normalizedVertices":[]},"paragraphs":[{"confidence":0.8521816730499268,"boundingBox":{"vertices":[{"x":329,"y":897},{"x":1193,"y":909},{"x":1190,"y":1124},{"x":326,"y":1112}],"normalizedVertices":[]},"words":[{"text":"July","confidence":0.8318085670471191,"boundingBox":{"vertices":[{"x":331,"y":897},{"x":465,"y":902},{"x":463,"y":960},{"x":329,"y":955}],"normalizedVertices":[]}},{"text":"10","confidence":0.46269160509109497,"boundingBox":{"vertices":[{"x":449,"y":902},{"x":515,"y":905},{"x":513,"y":963},{"x":447,"y":960}],"normalizedVertices":[]}},{"text":"Scott","confidence":0.796603262424469,"boundingBox":{"vertices":[{"x":583,"y":907},{"x":734,"y":913},{"x":732,"y":971},{"x":581,"y":965}],"normalizedVertices":[]}},{"text":"Joseph","confidence":0.9869624972343445,"boundingBox":{"vertices":[{"x":772,"y":915},{"x":948,"y":922},{"x":945,"y":980},{"x":770,"y":973}],"normalizedVertices":[]}},{"text":"Nagele","confidence":0.9261313676834106,"boundingBox":{"vertices":[{"x":967,"y":923},{"x":1134,"y":930},{"x":1132,"y":988},{"x":965,"y":981}],"normalizedVertices":[]}},{"text":"Washington","confidence":0.8109434247016907,"boundingBox":{"vertices":[{"x":590,"y":993},{"x":845,"y":993},{"x":845,"y":1040},{"x":590,"y":1040}],"normalizedVertices":[]}},{"text":"Township","confidence":0.7971051931381226,"boundingBox":{"vertices":[{"x":870,"y":993},{"x":1063,"y":993},{"x":1063,"y":1040},{"x":870,"y":1040}],"normalizedVertices":[]}},{"text":"N.J.","confidence":0.9830636978149414,"boundingBox":{"vertices":[{"x":1085,"y":993},{"x":1191,"y":993},{"x":1191,"y":1040},{"x":1085,"y":1040}],"normalizedVertices":[]}},{"text":"24","confidence":0.9599053859710693,"boundingBox":{"vertices":[{"x":603,"y":1073},{"x":693,"y":1073},{"x":693,"y":1116},{"x":603,"y":1116}],"normalizedVertices":[]}}]}]},{"blockType":"TEXT","confidence":0.966663122177124,"boundingBox":{"vertices":[{"x":1446,"y":808},{"x":1977,"y":851},{"x":1975,"y":874},{"x":1444,"y":831}],"normalizedVertices":[]},"paragraphs":[{"confidence":0.966663122177124,"boundingBox":{"vertices":[{"x":1446,"y":808},{"x":1977,"y":851},{"x":1975,"y":874},{"x":1444,"y":831}],"normalizedVertices":[]},"words":[{"text":"FULL","confidence":0.9853488206863403,"boundingBox":{"vertices":[{"x":1446,"y":808},{"x":1520,"y":814},{"x":1518,"y":837},{"x":1444,"y":831}],"normalizedVertices":[]}},{"text":"NAME","confidence":0.9913030862808228,"boundingBox":{"vertices":[{"x":1542,"y":816},{"x":1615,"y":822},{"x":1613,"y":845},{"x":1540,"y":839}],"normalizedVertices":[]}},{"text":"OF","confidence":0.9895094037055969,"boundingBox":{"vertices":[{"x":1634,"y":823},{"x":1671,"y":826},{"x":1669,"y":849},{"x":1632,"y":846}],"normalizedVertices":[]}},{"text":"BRIDE","confidence":0.9905121326446533,"boundingBox":{"vertices":[{"x":1690,"y":828},{"x":1779,"y":835},{"x":1777,"y":858},{"x":1688,"y":851}],"normalizedVertices":[]}},{"text":",","confidence":0.9701705574989319,"boundingBox":{"vertices":[{"x":1782,"y":836},{"x":1789,"y":837},{"x":1787,"y":858},{"x":1780,"y":858}],"normalizedVertices":[]}},{"text":"RESIDENCE","confidence":0.9810798764228821,"boundingBox":{"vertices":[{"x":1798,"y":837},{"x":1956,"y":850},{"x":1955,"y":872},{"x":1796,"y":859}],"normalizedVertices":[]}},{"text":".","confidence":0.49516499042510986,"boundingBox":{"vertices":[{"x":1967,"y":851},{"x":1977,"y":852},{"x":1975,"y":874},{"x":1965,"y":873}],"normalizedVertices":[]}}]}]},{"blockType":"TEXT","confidence":0.988307535648346,"boundingBox":{"vertices":[{"x":2014,"y":837},{"x":2177,"y":856},{"x":2174,"y":878},{"x":2011,"y":859}],"normalizedVertices":[]},"paragraphs":[{"confidence":0.988307535648346,"boundingBox":{"vertices":[{"x":2014,"y":837},{"x":2177,"y":856},{"x":2174,"y":878},{"x":2011,"y":859}],"normalizedVertices":[]},"words":[{"text":"FIRST","confidence":0.9850256443023682,"boundingBox":{"vertices":[{"x":2014,"y":837},{"x":2092,"y":846},{"x":2090,"y":868},{"x":2011,"y":859}],"normalizedVertices":[]}},{"text":"NAMES","confidence":0.991589367389679,"boundingBox":{"vertices":[{"x":2106,"y":848},{"x":2177,"y":856},{"x":2174,"y":878},{"x":2103,"y":870}],"normalizedVertices":[]}}]}]},{"blockType":"TEXT","confidence":0.9475863575935364,"boundingBox":{"vertices":[{"x":1228,"y":820},{"x":2163,"y":892},{"x":2161,"y":927},{"x":1225,"y":855}],"normalizedVertices":[]},"paragraphs":[{"confidence":0.9475863575935364,"boundingBox":{"vertices":[{"x":1228,"y":820},{"x":2163,"y":892},{"x":2161,"y":927},{"x":1225,"y":855}],"normalizedVertices":[]},"words":[{"text":"OF","confidence":0.9223926067352295,"boundingBox":{"vertices":[{"x":1228,"y":821},{"x":1265,"y":824},{"x":1262,"y":858},{"x":1225,"y":855}],"normalizedVertices":[]}},{"text":"GROOM'S","confidence":0.9653083682060242,"boundingBox":{"vertices":[{"x":1284,"y":825},{"x":1418,"y":835},{"x":1415,"y":869},{"x":1281,"y":859}],"normalizedVertices":[]}},{"text":"AGE","confidence":0.9470060467720032,"boundingBox":{"vertices":[{"x":1446,"y":837},{"x":1504,"y":841},{"x":1501,"y":876},{"x":1443,"y":872}],"normalizedVertices":[]}},{"text":",","confidence":0.7567231059074402,"boundingBox":{"vertices":[{"x":1505,"y":842},{"x":1514,"y":843},{"x":1511,"y":877},{"x":1502,"y":876}],"normalizedVertices":[]}},{"text":"RELIGION","confidence":0.9777310490608215,"boundingBox":{"vertices":[{"x":1521,"y":843},{"x":1662,"y":854},{"x":1659,"y":889},{"x":1518,"y":878}],"normalizedVertices":[]}},{"text":",","confidence":0.8188241720199585,"boundingBox":{"vertices":[{"x":1666,"y":854},{"x":1676,"y":855},{"x":1673,"y":889},{"x":1663,"y":888}],"normalizedVertices":[]}},{"text":"1st","confidence":0.7967058420181274,"boundingBox":{"vertices":[{"x":1694,"y":856},{"x":1742,"y":860},{"x":1739,"y":895},{"x":1691,"y":891}],"normalizedVertices":[]}},{"text":"or","confidence":0.9880882501602173,"boundingBox":{"vertices":[{"x":1754,"y":861},{"x":1790,"y":864},{"x":1787,"y":898},{"x":1751,"y":895}],"normalizedVertices":[]}},{"text":"2nd","confidence":0.9908105731010437,"boundingBox":{"vertices":[{"x":1800,"y":865},{"x":1844,"y":868},{"x":1841,"y":902},{"x":1797,"y":899}],"normalizedVertices":[]}},{"text":"MARRIAGE","confidence":0.9757325053215027,"boundingBox":{"vertices":[{"x":1852,"y":868},{"x":1995,"y":879},{"x":1992,"y":914},{"x":1849,"y":903}],"normalizedVertices":[]}},{"text":"OF","confidence":0.9361900091171265,"boundingBox":{"vertices":[{"x":2011,"y":881},{"x":2048,"y":884},{"x":2045,"y":918},{"x":2008,"y":915}],"normalizedVertices":[]}},{"text":"BRIDE'S","confidence":0.9541764855384827,"boundingBox":{"vertices":[{"x":2059,"y":884},{"x":2164,"y":892},{"x":2161,"y":927},{"x":2056,"y":919}],"normalizedVertices":[]}}]}]},{"blockType":"TEXT","confidence":0.9892295598983765,"boundingBox":{"vertices":[{"x":1264,"y":870},{"x":1397,"y":880},{"x":1395,"y":901},{"x":1262,"y":891}],"normalizedVertices":[]},"paragraphs":[{"confidence":0.9892295598983765,"boundingBox":{"vertices":[{"x":1264,"y":870},{"x":1397,"y":880},{"x":1395,"y":901},{"x":1262,"y":891}],"normalizedVertices":[]},"words":[{"text":"PARENTS","confidence":0.9892295598983765,"boundingBox":{"vertices":[{"x":1264,"y":870},{"x":1397,"y":880},{"x":1395,"y":901},{"x":1262,"y":891}],"normalizedVertices":[]}}]}]},{"blockType":"TEXT","confidence":0.9884026646614075,"boundingBox":{"vertices":[{"x":2043,"y":926},{"x":2146,"y":937},{"x":2144,"y":957},{"x":2041,"y":946}],"normalizedVertices":[]},"paragraphs":[{"confidence":0.9884026646614075,"boundingBox":{"vertices":[{"x":2043,"y":926},{"x":2146,"y":937},{"x":2144,"y":957},{"x":2041,"y":946}],"normalizedVertices":[]},"words":[{"text":"PARENTS","confidence":0.9884026646614075,"boundingBox":{"vertices":[{"x":2043,"y":926},{"x":2146,"y":937},{"x":2144,"y":957},{"x":2041,"y":946}],"normalizedVertices":[]}}]}]},{"blockType":"TEXT","confidence":0.7322001457214355,"boundingBox":{"vertices":[{"x":1233,"y":945},{"x":1372,"y":946},{"x":1372,"y":983},{"x":1233,"y":982}],"normalizedVertices":[]},"paragraphs":[{"confidence":0.7322001457214355,"boundingBox":{"vertices":[{"x":1233,"y":945},{"x":1372,"y":946},{"x":1372,"y":983},{"x":1233,"y":982}],"normalizedVertices":[]},"words":[{"text":"Robert","confidence":0.7322001457214355,"boundingBox":{"vertices":[{"x":1233,"y":945},{"x":1372,"y":946},{"x":1372,"y":983},{"x":1233,"y":982}],"normalizedVertices":[]}}]}]},{"blockType":"TEXT","confidence":0.5262359976768494,"boundingBox":{"vertices":[{"x":1487,"y":965},{"x":1805,"y":969},{"x":1805,"y":1006},{"x":1487,"y":1002}],"normalizedVertices":[]},"paragraphs":[{"confidence":0.5262359976768494,"boundingBox":{"vertices":[{"x":1487,"y":965},{"x":1805,"y":969},{"x":1805,"y":1006},{"x":1487,"y":1002}],"normalizedVertices":[]},"words":[{"text":"Ameruda","confidence":0.44727516174316406,"boundingBox":{"vertices":[{"x":1487,"y":965},{"x":1644,"y":967},{"x":1644,"y":1004},{"x":1487,"y":1002}],"normalizedVertices":[]}},{"text":"Savch","confidence":0.6367812156677246,"boundingBox":{"vertices":[{"x":1681,"y":967},{"x":1805,"y":968},{"x":1805,"y":1005},{"x":1681,"y":1004}],"normalizedVertices":[]}}]}]},{"blockType":"TEXT","confidence":0.6888147592544556,"boundingBox":{"vertices":[{"x":2019,"y":982},{"x":2155,"y":990},{"x":2153,"y":1023},{"x":2017,"y":1015}],"normalizedVertices":[]},"paragraphs":[{"confidence":0.6888147592544556,"boundingBox":{"vertices":[{"x":2019,"y":982},{"x":2155,"y":990},{"x":2153,"y":1023},{"x":2017,"y":1015}],"normalizedVertices":[]},"words":[{"text":"Robert","confidence":0.6888147592544556,"boundingBox":{"vertices":[{"x":2019,"y":982},{"x":2155,"y":990},{"x":2153,"y":1023},{"x":2017,"y":1015}],"normalizedVertices":[]}}]}]},{"blockType":"TEXT","confidence":0.8703387379646301,"boundingBox":{"vertices":[{"x":1234,"y":1023},{"x":1388,"y":1030},{"x":1386,"y":1067},{"x":1232,"y":1060}],"normalizedVertices":[]},"paragraphs":[{"confidence":0.8703387379646301,"boundingBox":{"vertices":[{"x":1234,"y":1023},{"x":1388,"y":1030},{"x":1386,"y":1067},{"x":1232,"y":1060}],"normalizedVertices":[]},"words":[{"text":"Kathleen","confidence":0.8703387379646301,"boundingBox":{"vertices":[{"x":1234,"y":1023},{"x":1388,"y":1030},{"x":1386,"y":1067},{"x":1232,"y":1060}],"normalizedVertices":[]}}]}]},{"blockType":"TEXT","confidence":0.8772253394126892,"boundingBox":{"vertices":[{"x":1491,"y":1032},{"x":1819,"y":1017},{"x":1821,"y":1072},{"x":1494,"y":1087}],"normalizedVertices":[]},"paragraphs":[{"confidence":0.8772253394126892,"boundingBox":{"vertices":[{"x":1491,"y":1032},{"x":1819,"y":1017},{"x":1821,"y":1072},{"x":1494,"y":1087}],"normalizedVertices":[]},"words":[{"text":"Manville","confidence":0.8350735902786255,"boundingBox":{"vertices":[{"x":1491,"y":1032},{"x":1691,"y":1023},{"x":1693,"y":1078},{"x":1494,"y":1087}],"normalizedVertices":[]}},{"text":",","confidence":0.9474911689758301,"boundingBox":{"vertices":[{"x":1684,"y":1024},{"x":1706,"y":1023},{"x":1708,"y":1077},{"x":1686,"y":1078}],"normalizedVertices":[]}},{"text":"N.J","confidence":0.9662081003189087,"boundingBox":{"vertices":[{"x":1728,"y":1021},{"x":1819,"y":1017},{"x":1821,"y":1072},{"x":1731,"y":1076}],"normalizedVertices":[]}}]}]},{"blockType":"TEXT","confidence":0.5678263902664185,"boundingBox":{"vertices":[{"x":2016,"y":1041},{"x":2131,"y":1051},{"x":2125,"y":1112},{"x":2011,"y":1102}],"normalizedVertices":[]},"paragraphs":[{"confidence":0.5678263902664185,"boundingBox":{"vertices":[{"x":2016,"y":1041},{"x":2131,"y":1051},{"x":2125,"y":1112},{"x":2011,"y":1102}],"normalizedVertices":[]},"words":[{"text":"stray","confidence":0.5678263902664185,"boundingBox":{"vertices":[{"x":2016,"y":1041},{"x":2131,"y":1051},{"x":2125,"y":1112},{"x":2011,"y":1102}],"normalizedVertices":[]}}]}]},{"blockType":"TEXT","confidence":0.8588540554046631,"boundingBox":{"vertices":[{"x":1491,"y":1107},{"x":1667,"y":1106},{"x":1667,"y":1190},{"x":1491,"y":1191}],"normalizedVertices":[]},"paragraphs":[{"confidence":0.8588540554046631,"boundingBox":{"vertices":[{"x":1491,"y":1107},{"x":1667,"y":1106},{"x":1667,"y":1190},{"x":1491,"y":1191}],"normalizedVertices":[]},"words":[{"text":"34","confidence":0.950737476348877,"boundingBox":{"vertices":[{"x":1495,"y":1107},{"x":1565,"y":1106},{"x":1565,"y":1139},{"x":1495,"y":1140}],"normalizedVertices":[]}},{"text":"Orthodox","confidence":0.8358832001686096,"boundingBox":{"vertices":[{"x":1491,"y":1149},{"x":1667,"y":1149},{"x":1667,"y":1190},{"x":1491,"y":1190}],"normalizedVertices":[]}}]}]},{"blockType":"TEXT","confidence":0.6399080157279968,"boundingBox":{"vertices":[{"x":589,"y":1143},{"x":940,"y":1146},{"x":940,"y":1189},{"x":589,"y":1186}],"normalizedVertices":[]},"paragraphs":[{"confidence":0.6399080157279968,"boundingBox":{"vertices":[{"x":589,"y":1143},{"x":940,"y":1146},{"x":940,"y":1189},{"x":589,"y":1186}],"normalizedVertices":[]},"words":[{"text":"Roman","confidence":0.6444814801216125,"boundingBox":{"vertices":[{"x":589,"y":1143},{"x":741,"y":1144},{"x":741,"y":1187},{"x":589,"y":1186}],"normalizedVertices":[]}},{"text":"Catholic","confidence":0.6370495557785034,"boundingBox":{"vertices":[{"x":780,"y":1145},{"x":940,"y":1146},{"x":940,"y":1188},{"x":780,"y":1187}],"normalizedVertices":[]}}]}]},{"blockType":"TEXT","confidence":0.9896048903465271,"boundingBox":{"vertices":[{"x":2408,"y":49},{"x":2691,"y":24},{"x":2697,"y":95},{"x":2414,"y":121}],"normalizedVertices":[]},"paragraphs":[{"confidence":0.9896048903465271,"boundingBox":{"vertices":[{"x":2408,"y":49},{"x":2691,"y":24},{"x":2697,"y":95},{"x":2414,"y":121}],"normalizedVertices":[]},"words":[{"text":"YEAR","confidence":0.9896048903465271,"boundingBox":{"vertices":[{"x":2408,"y":49},{"x":2691,"y":24},{"x":2697,"y":95},{"x":2414,"y":121}],"normalizedVertices":[]}}]}]},{"blockType":"TEXT","confidence":0.6892798542976379,"boundingBox":{"vertices":[{"x":3051,"y":91},{"x":3073,"y":91},{"x":3073,"y":112},{"x":3051,"y":112}],"normalizedVertices":[]},"paragraphs":[{"confidence":0.6892798542976379,"boundingBox":{"vertices":[{"x":3051,"y":91},{"x":3073,"y":91},{"x":3073,"y":112},{"x":3051,"y":112}],"normalizedVertices":[]},"words":[{"text":"H","confidence":0.6892798542976379,"boundingBox":{"vertices":[{"x":3051,"y":91},{"x":3073,"y":91},{"x":3073,"y":112},{"x":3051,"y":112}],"normalizedVertices":[]}}]}]},{"blockType":"TEXT","confidence":0.3880137801170349,"boundingBox":{"vertices":[{"x":2252,"y":234},{"x":3507,"y":157},{"x":3518,"y":344},{"x":2263,"y":421}],"normalizedVertices":[]},"paragraphs":[{"confidence":0.3880137801170349,"boundingBox":{"vertices":[{"x":2252,"y":234},{"x":3507,"y":157},{"x":3518,"y":344},{"x":2263,"y":421}],"normalizedVertices":[]},"words":[{"text":"MM","confidence":0.2973133325576782,"boundingBox":{"vertices":[{"x":2255,"y":283},{"x":2337,"y":261},{"x":2356,"y":334},{"x":2274,"y":355}],"normalizedVertices":[]}},{"text":",","confidence":0.34883299469947815,"boundingBox":{"vertices":[{"x":2340,"y":273},{"x":2375,"y":264},{"x":2390,"y":321},{"x":2355,"y":330}],"normalizedVertices":[]}},{"text":"CTL","confidence":0.6160986423492432,"boundingBox":{"vertices":[{"x":2458,"y":221},{"x":2594,"y":214},{"x":2598,"y":293},{"x":2462,"y":300}],"normalizedVertices":[]}},{"text":"FTSFAN","confidence":0.3604358434677124,"boundingBox":{"vertices":[{"x":2626,"y":212},{"x":2861,"y":210},{"x":2862,"y":291},{"x":2627,"y":293}],"normalizedVertices":[]}},{"text":",","confidence":0.5851737260818481,"boundingBox":{"vertices":[{"x":2855,"y":252},{"x":2875,"y":252},{"x":2875,"y":292},{"x":2855,"y":292}],"normalizedVertices":[]}},{"text":"(","confidence":0.3926548659801483,"boundingBox":{"vertices":[{"x":2912,"y":211},{"x":2947,"y":212},{"x":2944,"y":292},{"x":2909,"y":291}],"normalizedVertices":[]}},{"text":"GPESCS4CTAHUNGE","confidence":0.35468006134033203,"boundingBox":{"vertices":[{"x":2991,"y":219},{"x":3513,"y":266},{"x":3506,"y":344},{"x":2984,"y":298}],"normalizedVertices":[]}}]}]},{"blockType":"TEXT","confidence":0.42974182963371277,"boundingBox":{"vertices":[{"x":2299,"y":555},{"x":2526,"y":531},{"x":2529,"y":561},{"x":2302,"y":586}],"normalizedVertices":[]},"paragraphs":[{"confidence":0.42974182963371277,"boundingBox":{"vertices":[{"x":2299,"y":555},{"x":2526,"y":531},{"x":2529,"y":561},{"x":2302,"y":586}],"normalizedVertices":[]},"words":[{"text":"KTO","confidence":0.43368449807167053,"boundingBox":{"vertices":[{"x":2299,"y":556},{"x":2349,"y":551},{"x":2352,"y":580},{"x":2302,"y":586}],"normalizedVertices":[]}},{"text":"COREOшAAZ","confidence":0.4284276068210602,"boundingBox":{"vertices":[{"x":2367,"y":548},{"x":2526,"y":531},{"x":2529,"y":561},{"x":2370,"y":578}],"normalizedVertices":[]}}]}]},{"blockType":"TEXT","confidence":0.951824963092804,"boundingBox":{"vertices":[{"x":2346,"y":644},{"x":2490,"y":627},{"x":2493,"y":649},{"x":2349,"y":666}],"normalizedVertices":[]},"paragraphs":[{"confidence":0.951824963092804,"boundingBox":{"vertices":[{"x":2346,"y":644},{"x":2490,"y":627},{"x":2493,"y":649},{"x":2349,"y":666}],"normalizedVertices":[]},"words":[{"text":"таинство","confidence":0.9468942284584045,"boundingBox":{"vertices":[{"x":2346,"y":644},{"x":2481,"y":628},{"x":2484,"y":650},{"x":2349,"y":666}],"normalizedVertices":[]}},{"text":".","confidence":0.9912711381912231,"boundingBox":{"vertices":[{"x":2482,"y":628},{"x":2490,"y":627},{"x":2492,"y":648},{"x":2485,"y":649}],"normalizedVertices":[]}}]}]},{"blockType":"TEXT","confidence":0.9819924235343933,"boundingBox":{"vertices":[{"x":2320,"y":857},{"x":2540,"y":841},{"x":2542,"y":864},{"x":2322,"y":880}],"normalizedVertices":[]},"paragraphs":[{"confidence":0.9819924235343933,"boundingBox":{"vertices":[{"x":2320,"y":857},{"x":2540,"y":841},{"x":2542,"y":864},{"x":2322,"y":880}],"normalizedVertices":[]},"words":[{"text":"PRIEST'S","confidence":0.9761046171188354,"boundingBox":{"vertices":[{"x":2320,"y":857},{"x":2448,"y":848},{"x":2449,"y":871},{"x":2322,"y":880}],"normalizedVertices":[]}},{"text":"NAME","confidence":0.9937679767608643,"boundingBox":{"vertices":[{"x":2466,"y":846},{"x":2541,"y":841},{"x":2542,"y":863},{"x":2468,"y":869}],"normalizedVertices":[]}}]}]},{"blockType":"TEXT","confidence":0.9626557230949402,"boundingBox":{"vertices":[{"x":2815,"y":568},{"x":3272,"y":600},{"x":3269,"y":636},{"x":2812,"y":604}],"normalizedVertices":[]},"paragraphs":[{"confidence":0.9626557230949402,"boundingBox":{"vertices":[{"x":2815,"y":568},{"x":3272,"y":600},{"x":3269,"y":636},{"x":2812,"y":604}],"normalizedVertices":[]},"words":[{"text":"Кто","confidence":0.9609767198562622,"boundingBox":{"vertices":[{"x":2815,"y":568},{"x":2898,"y":574},{"x":2895,"y":610},{"x":2812,"y":604}],"normalizedVertices":[]}},{"text":"были","confidence":0.9231084585189819,"boundingBox":{"vertices":[{"x":2920,"y":575},{"x":3018,"y":582},{"x":3015,"y":618},{"x":2917,"y":611}],"normalizedVertices":[]}},{"text":"поручители","confidence":0.9782634377479553,"boundingBox":{"vertices":[{"x":3039,"y":584},{"x":3263,"y":600},{"x":3261,"y":636},{"x":3036,"y":620}],"normalizedVertices":[]}},{"text":".","confidence":0.9698043465614319,"boundingBox":{"vertices":[{"x":3265,"y":600},{"x":3272,"y":600},{"x":3270,"y":635},{"x":3263,"y":635}],"normalizedVertices":[]}}]}]},{"blockType":"TEXT","confidence":0.9884705543518066,"boundingBox":{"vertices":[{"x":2906,"y":840},{"x":3160,"y":853},{"x":3158,"y":877},{"x":2905,"y":864}],"normalizedVertices":[]},"paragraphs":[{"confidence":0.9884705543518066,"boundingBox":{"vertices":[{"x":2906,"y":840},{"x":3160,"y":853},{"x":3158,"y":877},{"x":2905,"y":864}],"normalizedVertices":[]},"words":[{"text":"WITNESSES","confidence":0.9884821176528931,"boundingBox":{"vertices":[{"x":2906,"y":840},{"x":3060,"y":848},{"x":3059,"y":872},{"x":2905,"y":864}],"normalizedVertices":[]}},{"text":"NAMES","confidence":0.98844975233078,"boundingBox":{"vertices":[{"x":3076,"y":848},{"x":3160,"y":852},{"x":3159,"y":876},{"x":3075,"y":872}],"normalizedVertices":[]}}]}]},{"blockType":"TEXT","confidence":0.9302886128425598,"boundingBox":{"vertices":[{"x":3508,"y":560},{"x":3998,"y":589},{"x":3996,"y":622},{"x":3506,"y":593}],"normalizedVertices":[]},"paragraphs":[{"confidence":0.9302886128425598,"boundingBox":{"vertices":[{"x":3508,"y":560},{"x":3998,"y":589},{"x":3996,"y":622},{"x":3506,"y":593}],"normalizedVertices":[]},"words":[{"text":"Отя","confidence":0.7965506315231323,"boundingBox":{"vertices":[{"x":3508,"y":560},{"x":3570,"y":564},{"x":3568,"y":597},{"x":3506,"y":593}],"normalizedVertices":[]}},{"text":"какого","confidence":0.9772531390190125,"boundingBox":{"vertices":[{"x":3589,"y":565},{"x":3681,"y":570},{"x":3679,"y":602},{"x":3587,"y":597}],"normalizedVertices":[]}},{"text":"числа","confidence":0.9903345108032227,"boundingBox":{"vertices":[{"x":3707,"y":572},{"x":3784,"y":577},{"x":3782,"y":609},{"x":3705,"y":604}],"normalizedVertices":[]}},{"text":"и","confidence":0.9614647626876831,"boundingBox":{"vertices":[{"x":3802,"y":578},{"x":3820,"y":579},{"x":3818,"y":611},{"x":3800,"y":610}],"normalizedVertices":[]}},{"text":"за","confidence":0.9828848838806152,"boundingBox":{"vertices":[{"x":3839,"y":580},{"x":3873,"y":582},{"x":3871,"y":614},{"x":3837,"y":612}],"normalizedVertices":[]}},{"text":"какимя","confidence":0.8774267435073853,"boundingBox":{"vertices":[{"x":3891,"y":583},{"x":3998,"y":589},{"x":3996,"y":622},{"x":3889,"y":616}],"normalizedVertices":[]}}]}]},{"blockType":"TEXT","confidence":0.8923741579055786,"boundingBox":{"vertices":[{"x":3660,"y":655},{"x":3847,"y":663},{"x":3845,"y":697},{"x":3659,"y":689}],"normalizedVertices":[]},"paragraphs":[{"confidence":0.8923741579055786,"boundingBox":{"vertices":[{"x":3660,"y":655},{"x":3847,"y":663},{"x":3845,"y":697},{"x":3659,"y":689}],"normalizedVertices":[]},"words":[{"text":"№","confidence":0.1640128642320633,"boundingBox":{"vertices":[{"x":3660,"y":656},{"x":3689,"y":657},{"x":3688,"y":690},{"x":3659,"y":689}],"normalizedVertices":[]}},{"text":"License","confidence":0.9885051250457764,"boundingBox":{"vertices":[{"x":3712,"y":657},{"x":3839,"y":662},{"x":3838,"y":696},{"x":3711,"y":691}],"normalizedVertices":[]}},{"text":".","confidence":0.9478186368942261,"boundingBox":{"vertices":[{"x":3837,"y":663},{"x":3847,"y":663},{"x":3846,"y":696},{"x":3836,"y":696}],"normalizedVertices":[]}}]}]},{"blockType":"TEXT","confidence":0.6148781180381775,"boundingBox":{"vertices":[{"x":2304,"y":967},{"x":2509,"y":967},{"x":2509,"y":1093},{"x":2304,"y":1093}],"normalizedVertices":[]},"paragraphs":[{"confidence":0.6148781180381775,"boundingBox":{"vertices":[{"x":2304,"y":967},{"x":2509,"y":967},{"x":2509,"y":1093},{"x":2304,"y":1093}],"normalizedVertices":[]},"words":[{"text":"For","confidence":0.589530885219574,"boundingBox":{"vertices":[{"x":2307,"y":967},{"x":2378,"y":970},{"x":2375,"y":1036},{"x":2304,"y":1033}],"normalizedVertices":[]}},{"text":"Jas","confidence":0.47426724433898926,"boundingBox":{"vertices":[{"x":2383,"y":970},{"x":2509,"y":975},{"x":2506,"y":1041},{"x":2380,"y":1036}],"normalizedVertices":[]}},{"text":"Parell","confidence":0.6978572607040405,"boundingBox":{"vertices":[{"x":2352,"y":1038},{"x":2504,"y":1032},{"x":2506,"y":1087},{"x":2354,"y":1093}],"normalizedVertices":[]}}]}]},{"blockType":"TEXT","confidence":0.7783305644989014,"boundingBox":{"vertices":[{"x":2698,"y":950},{"x":3181,"y":957},{"x":3179,"y":1090},{"x":2696,"y":1083}],"normalizedVertices":[]},"paragraphs":[{"confidence":0.7809644937515259,"boundingBox":{"vertices":[{"x":2700,"y":950},{"x":3021,"y":964},{"x":3018,"y":1019},{"x":2698,"y":1005}],"normalizedVertices":[]},"words":[{"text":"Eric","confidence":0.5712692737579346,"boundingBox":{"vertices":[{"x":2700,"y":950},{"x":2816,"y":955},{"x":2814,"y":1010},{"x":2698,"y":1005}],"normalizedVertices":[]}},{"text":"Nagele","confidence":0.920761227607727,"boundingBox":{"vertices":[{"x":2854,"y":957},{"x":3021,"y":964},{"x":3018,"y":1019},{"x":2852,"y":1012}],"normalizedVertices":[]}}]},{"confidence":0.7768672704696655,"boundingBox":{"vertices":[{"x":2700,"y":1044},{"x":3179,"y":1037},{"x":3180,"y":1076},{"x":2701,"y":1083}],"normalizedVertices":[]},"words":[{"text":"Katherine","confidence":0.7514190673828125,"boundingBox":{"vertices":[{"x":2700,"y":1044},{"x":2928,"y":1040},{"x":2929,"y":1079},{"x":2701,"y":1083}],"normalizedVertices":[]}},{"text":"markerich","confidence":0.8023155331611633,"boundingBox":{"vertices":[{"x":2955,"y":1040},{"x":3179,"y":1037},{"x":3180,"y":1076},{"x":2956,"y":1079}],"normalizedVertices":[]}}]}]},{"blockType":"TEXT","confidence":0.9854576587677002,"boundingBox":{"vertices":[{"x":3567,"y":871},{"x":3976,"y":883},{"x":3975,"y":905},{"x":3566,"y":893}],"normalizedVertices":[]},"paragraphs":[{"confidence":0.9854576587677002,"boundingBox":{"vertices":[{"x":3567,"y":871},{"x":3976,"y":883},{"x":3975,"y":905},{"x":3566,"y":893}],"normalizedVertices":[]},"words":[{"text":"DATE","confidence":0.9879069328308105,"boundingBox":{"vertices":[{"x":3567,"y":871},{"x":3629,"y":873},{"x":3628,"y":895},{"x":3566,"y":893}],"normalizedVertices":[]}},{"text":"AND","confidence":0.9902892708778381,"boundingBox":{"vertices":[{"x":3643,"y":874},{"x":3690,"y":875},{"x":3689,"y":896},{"x":3642,"y":895}],"normalizedVertices":[]}},{"text":"NUMBER","confidence":0.9831944108009338,"boundingBox":{"vertices":[{"x":3706,"y":875},{"x":3801,"y":878},{"x":3800,"y":900},{"x":3705,"y":897}],"normalizedVertices":[]}},{"text":"OF","confidence":0.988445520401001,"boundingBox":{"vertices":[{"x":3817,"y":879},{"x":3848,"y":880},{"x":3847,"y":901},{"x":3816,"y":900}],"normalizedVertices":[]}},{"text":"LICENSE","confidence":0.9830737113952637,"boundingBox":{"vertices":[{"x":3864,"y":880},{"x":3976,"y":883},{"x":3975,"y":905},{"x":3863,"y":902}],"normalizedVertices":[]}}]}]},{"blockType":"TEXT","confidence":0.9619343280792236,"boundingBox":{"vertices":[{"x":3497,"y":977},{"x":3798,"y":965},{"x":3803,"y":1088},{"x":3502,"y":1100}],"normalizedVertices":[]},"paragraphs":[{"confidence":0.9910445213317871,"boundingBox":{"vertices":[{"x":3520,"y":976},{"x":3745,"y":970},{"x":3746,"y":1012},{"x":3521,"y":1018}],"normalizedVertices":[]},"words":[{"text":"6-28-2011","confidence":0.9910445213317871,"boundingBox":{"vertices":[{"x":3520,"y":976},{"x":3745,"y":970},{"x":3746,"y":1012},{"x":3521,"y":1018}],"normalizedVertices":[]}}]},{"confidence":0.9328241348266602,"boundingBox":{"vertices":[{"x":3500,"y":1058},{"x":3800,"y":1042},{"x":3802,"y":1083},{"x":3502,"y":1100}],"normalizedVertices":[]},"words":[{"text":"MC","confidence":0.7636801600456238,"boundingBox":{"vertices":[{"x":3500,"y":1058},{"x":3592,"y":1053},{"x":3594,"y":1095},{"x":3502,"y":1100}],"normalizedVertices":[]}},{"text":"29-2011","confidence":0.9811509847640991,"boundingBox":{"vertices":[{"x":3608,"y":1052},{"x":3800,"y":1041},{"x":3802,"y":1083},{"x":3610,"y":1094}],"normalizedVertices":[]}}]}]},{"blockType":"TEXT","confidence":0.9174237847328186,"boundingBox":{"vertices":[{"x":121,"y":1401},{"x":178,"y":1401},{"x":178,"y":1449},{"x":121,"y":1449}],"normalizedVertices":[]},"paragraphs":[{"confidence":0.9174237847328186,"boundingBox":{"vertices":[{"x":121,"y":1401},{"x":178,"y":1401},{"x":178,"y":1449},{"x":121,"y":1449}],"normalizedVertices":[]},"words":[{"text":"2","confidence":0.9174237847328186,"boundingBox":{"vertices":[{"x":121,"y":1401},{"x":178,"y":1401},{"x":178,"y":1449},{"x":121,"y":1449}],"normalizedVertices":[]}}]}]},{"blockType":"TEXT","confidence":0.8500732779502869,"boundingBox":{"vertices":[{"x":304,"y":1390},{"x":1190,"y":1374},{"x":1191,"y":1441},{"x":305,"y":1457}],"normalizedVertices":[]},"paragraphs":[{"confidence":0.8500732779502869,"boundingBox":{"vertices":[{"x":304,"y":1390},{"x":1190,"y":1374},{"x":1191,"y":1441},{"x":305,"y":1457}],"normalizedVertices":[]},"words":[{"text":"July","confidence":0.9647628664970398,"boundingBox":{"vertices":[{"x":304,"y":1390},{"x":437,"y":1388},{"x":438,"y":1455},{"x":305,"y":1457}],"normalizedVertices":[]}},{"text":"17","confidence":0.9118300676345825,"boundingBox":{"vertices":[{"x":445,"y":1388},{"x":499,"y":1387},{"x":500,"y":1453},{"x":446,"y":1454}],"normalizedVertices":[]}},{"text":"Christopher","confidence":0.8878012895584106,"boundingBox":{"vertices":[{"x":545,"y":1386},{"x":832,"y":1381},{"x":833,"y":1447},{"x":546,"y":1452}],"normalizedVertices":[]}},{"text":"Michel","confidence":0.7725764513015747,"boundingBox":{"vertices":[{"x":852,"y":1380},{"x":1039,"y":1377},{"x":1040,"y":1444},{"x":853,"y":1447}],"normalizedVertices":[]}},{"text":"Brooks","confidence":0.761356770992279,"boundingBox":{"vertices":[{"x":1042,"y":1377},{"x":1190,"y":1374},{"x":1191,"y":1440},{"x":1043,"y":1443}],"normalizedVertices":[]}}]}]},{"blockType":"TEXT","confidence":0.7786829471588135,"boundingBox":{"vertices":[{"x":1223,"y":1419},{"x":1388,"y":1415},{"x":1389,"y":1453},{"x":1224,"y":1457}],"normalizedVertices":[]},"paragraphs":[{"confidence":0.7786829471588135,"boundingBox":{"vertices":[{"x":1223,"y":1419},{"x":1388,"y":1415},{"x":1389,"y":1453},{"x":1224,"y":1457}],"normalizedVertices":[]},"words":[{"text":"Ronald","confidence":0.7786829471588135,"boundingBox":{"vertices":[{"x":1223,"y":1419},{"x":1388,"y":1415},{"x":1389,"y":1453},{"x":1224,"y":1457}],"normalizedVertices":[]}}]}]},{"blockType":"TEXT","confidence":0.769455075263977,"boundingBox":{"vertices":[{"x":1509,"y":1396},{"x":2114,"y":1391},{"x":2114,"y":1436},{"x":1509,"y":1441}],"normalizedVertices":[]},"paragraphs":[{"confidence":0.769455075263977,"boundingBox":{"vertices":[{"x":1509,"y":1396},{"x":2114,"y":1391},{"x":2114,"y":1436},{"x":1509,"y":1441}],"normalizedVertices":[]},"words":[{"text":"Catherine","confidence":0.9055821299552917,"boundingBox":{"vertices":[{"x":1509,"y":1396},{"x":1723,"y":1394},{"x":1723,"y":1439},{"x":1509,"y":1441}],"normalizedVertices":[]}},{"text":"Gorbztuk","confidence":0.6633104085922241,"boundingBox":{"vertices":[{"x":1759,"y":1394},{"x":1952,"y":1392},{"x":1952,"y":1437},{"x":1759,"y":1439}],"normalizedVertices":[]}},{"text":"Peter","confidence":0.6942579746246338,"boundingBox":{"vertices":[{"x":2011,"y":1391},{"x":2114,"y":1390},{"x":2114,"y":1435},{"x":2011,"y":1436}],"normalizedVertices":[]}}]}]},{"blockType":"TEXT","confidence":0.6983951926231384,"boundingBox":{"vertices":[{"x":575,"y":1474},{"x":1050,"y":1478},{"x":1049,"y":1540},{"x":574,"y":1536}],"normalizedVertices":[]},"paragraphs":[{"confidence":0.6983951926231384,"boundingBox":{"vertices":[{"x":575,"y":1474},{"x":1050,"y":1478},{"x":1049,"y":1540},{"x":574,"y":1536}],"normalizedVertices":[]},"words":[{"text":"No.","confidence":0.7749859094619751,"boundingBox":{"vertices":[{"x":575,"y":1474},{"x":697,"y":1475},{"x":696,"y":1537},{"x":574,"y":1536}],"normalizedVertices":[]}},{"text":"Brunswick","confidence":0.6049281358718872,"boundingBox":{"vertices":[{"x":687,"y":1475},{"x":922,"y":1477},{"x":921,"y":1539},{"x":686,"y":1537}],"normalizedVertices":[]}},{"text":",","confidence":0.8660598993301392,"boundingBox":{"vertices":[{"x":916,"y":1478},{"x":943,"y":1478},{"x":942,"y":1539},{"x":915,"y":1539}],"normalizedVertices":[]}},{"text":"NJ","confidence":0.9202784299850464,"boundingBox":{"vertices":[{"x":959,"y":1478},{"x":1050,"y":1479},{"x":1049,"y":1541},{"x":958,"y":1540}],"normalizedVertices":[]}}]}]},{"blockType":"TEXT","confidence":0.4863489270210266,"boundingBox":{"vertices":[{"x":2019,"y":1469},{"x":2128,"y":1470},{"x":2128,"y":1500},{"x":2019,"y":1499}],"normalizedVertices":[]},"paragraphs":[{"confidence":0.4863489270210266,"boundingBox":{"vertices":[{"x":2019,"y":1469},{"x":2128,"y":1470},{"x":2128,"y":1500},{"x":2019,"y":1499}],"normalizedVertices":[]},"words":[{"text":"Suszy","confidence":0.4863489270210266,"boundingBox":{"vertices":[{"x":2019,"y":1469},{"x":2128,"y":1470},{"x":2128,"y":1500},{"x":2019,"y":1499}],"normalizedVertices":[]}}]}]},{"blockType":"TEXT","confidence":0.4213511645793915,"boundingBox":{"vertices":[{"x":1253,"y":1495},{"x":1362,"y":1495},{"x":1362,"y":1527},{"x":1253,"y":1527}],"normalizedVertices":[]},"paragraphs":[{"confidence":0.4213511645793915,"boundingBox":{"vertices":[{"x":1253,"y":1495},{"x":1362,"y":1495},{"x":1362,"y":1527},{"x":1253,"y":1527}],"normalizedVertices":[]},"words":[{"text":"C2101","confidence":0.4213511645793915,"boundingBox":{"vertices":[{"x":1253,"y":1495},{"x":1362,"y":1495},{"x":1362,"y":1527},{"x":1253,"y":1527}],"normalizedVertices":[]}}]}]},{"blockType":"TEXT","confidence":0.7840114831924438,"boundingBox":{"vertices":[{"x":1503,"y":1488},{"x":1875,"y":1482},{"x":1876,"y":1541},{"x":1504,"y":1547}],"normalizedVertices":[]},"paragraphs":[{"confidence":0.7840114831924438,"boundingBox":{"vertices":[{"x":1503,"y":1488},{"x":1875,"y":1482},{"x":1876,"y":1541},{"x":1504,"y":1547}],"normalizedVertices":[]},"words":[{"text":"Manville","confidence":0.7876423597335815,"boundingBox":{"vertices":[{"x":1503,"y":1488},{"x":1708,"y":1484},{"x":1709,"y":1543},{"x":1504,"y":1547}],"normalizedVertices":[]}},{"text":",","confidence":0.8848177194595337,"boundingBox":{"vertices":[{"x":1705,"y":1485},{"x":1729,"y":1485},{"x":1730,"y":1543},{"x":1706,"y":1543}],"normalizedVertices":[]}},{"text":"NJ","confidence":0.6835025548934937,"boundingBox":{"vertices":[{"x":1764,"y":1484},{"x":1845,"y":1483},{"x":1846,"y":1541},{"x":1765,"y":1542}],"normalizedVertices":[]}},{"text":".","confidence":0.8551759719848633,"boundingBox":{"vertices":[{"x":1848,"y":1483},{"x":1875,"y":1483},{"x":1876,"y":1541},{"x":1849,"y":1541}],"normalizedVertices":[]}}]}]},{"blockType":"TEXT","confidence":0.6289675831794739,"boundingBox":{"vertices":[{"x":2315,"y":1388},{"x":2467,"y":1385},{"x":2469,"y":1508},{"x":2318,"y":1511}],"normalizedVertices":[]},"paragraphs":[{"confidence":0.6289675831794739,"boundingBox":{"vertices":[{"x":2315,"y":1388},{"x":2467,"y":1385},{"x":2469,"y":1508},{"x":2318,"y":1511}],"normalizedVertices":[]},"words":[{"text":"Fr.","confidence":0.685245156288147,"boundingBox":{"vertices":[{"x":2316,"y":1388},{"x":2380,"y":1387},{"x":2381,"y":1440},{"x":2317,"y":1441}],"normalizedVertices":[]}},{"text":"Pards","confidence":0.5952010750770569,"boundingBox":{"vertices":[{"x":2318,"y":1458},{"x":2467,"y":1453},{"x":2469,"y":1506},{"x":2320,"y":1511}],"normalizedVertices":[]}}]}]},{"blockType":"TEXT","confidence":0.7807038426399231,"boundingBox":{"vertices":[{"x":2410,"y":1365},{"x":2522,"y":1368},{"x":2520,"y":1450},{"x":2408,"y":1447}],"normalizedVertices":[]},"paragraphs":[{"confidence":0.7807038426399231,"boundingBox":{"vertices":[{"x":2410,"y":1365},{"x":2522,"y":1368},{"x":2520,"y":1450},{"x":2408,"y":1447}],"normalizedVertices":[]},"words":[{"text":"да","confidence":0.7807038426399231,"boundingBox":{"vertices":[{"x":2410,"y":1365},{"x":2522,"y":1368},{"x":2520,"y":1450},{"x":2408,"y":1447}],"normalizedVertices":[]}}]}]},{"blockType":"TEXT","confidence":0.8695387840270996,"boundingBox":{"vertices":[{"x":615,"y":1573},{"x":708,"y":1572},{"x":708,"y":1607},{"x":615,"y":1608}],"normalizedVertices":[]},"paragraphs":[{"confidence":0.8695387840270996,"boundingBox":{"vertices":[{"x":615,"y":1573},{"x":708,"y":1572},{"x":708,"y":1607},{"x":615,"y":1608}],"normalizedVertices":[]},"words":[{"text":"25","confidence":0.8695387840270996,"boundingBox":{"vertices":[{"x":615,"y":1573},{"x":708,"y":1572},{"x":708,"y":1607},{"x":615,"y":1608}],"normalizedVertices":[]}}]}]},{"blockType":"TEXT","confidence":0.5826035141944885,"boundingBox":{"vertices":[{"x":579,"y":1638},{"x":977,"y":1614},{"x":980,"y":1666},{"x":582,"y":1690}],"normalizedVertices":[]},"paragraphs":[{"confidence":0.5826035141944885,"boundingBox":{"vertices":[{"x":579,"y":1638},{"x":977,"y":1614},{"x":980,"y":1666},{"x":582,"y":1690}],"normalizedVertices":[]},"words":[{"text":"Roman","confidence":0.45708203315734863,"boundingBox":{"vertices":[{"x":579,"y":1638},{"x":733,"y":1629},{"x":736,"y":1681},{"x":582,"y":1690}],"normalizedVertices":[]}},{"text":"Catholic","confidence":0.6610544919967651,"boundingBox":{"vertices":[{"x":795,"y":1625},{"x":978,"y":1614},{"x":981,"y":1666},{"x":798,"y":1677}],"normalizedVertices":[]}}]}]},{"blockType":"TEXT","confidence":0.9298202991485596,"boundingBox":{"vertices":[{"x":1518,"y":1575},{"x":1608,"y":1578},{"x":1607,"y":1610},{"x":1517,"y":1607}],"normalizedVertices":[]},"paragraphs":[{"confidence":0.9298202991485596,"boundingBox":{"vertices":[{"x":1518,"y":1575},{"x":1608,"y":1578},{"x":1607,"y":1610},{"x":1517,"y":1607}],"normalizedVertices":[]},"words":[{"text":"25","confidence":0.9298202991485596,"boundingBox":{"vertices":[{"x":1518,"y":1575},{"x":1608,"y":1578},{"x":1607,"y":1610},{"x":1517,"y":1607}],"normalizedVertices":[]}}]}]},{"blockType":"TEXT","confidence":0.6229591965675354,"boundingBox":{"vertices":[{"x":2660,"y":1351},{"x":3105,"y":1330},{"x":3112,"y":1467},{"x":2667,"y":1488}],"normalizedVertices":[]},"paragraphs":[{"confidence":0.6229591965675354,"boundingBox":{"vertices":[{"x":2660,"y":1351},{"x":3105,"y":1330},{"x":3112,"y":1467},{"x":2667,"y":1488}],"normalizedVertices":[]},"words":[{"text":"Timothy","confidence":0.8015018701553345,"boundingBox":{"vertices":[{"x":2660,"y":1357},{"x":2848,"y":1346},{"x":2851,"y":1407},{"x":2664,"y":1419}],"normalizedVertices":[]}},{"text":"Gorbetun","confidence":0.5502834916114807,"boundingBox":{"vertices":[{"x":2912,"y":1342},{"x":3105,"y":1330},{"x":3108,"y":1392},{"x":2916,"y":1404}],"normalizedVertices":[]}},{"text":"Rebeca","confidence":0.7571132183074951,"boundingBox":{"vertices":[{"x":2684,"y":1435},{"x":2856,"y":1429},{"x":2858,"y":1476},{"x":2686,"y":1482}],"normalizedVertices":[]}},{"text":"Gorbitay","confidence":0.4387945532798767,"boundingBox":{"vertices":[{"x":2918,"y":1427},{"x":3092,"y":1421},{"x":3094,"y":1468},{"x":2920,"y":1474}],"normalizedVertices":[]}}]}]},{"blockType":"TEXT","confidence":0.9728249311447144,"boundingBox":{"vertices":[{"x":3516,"y":1285},{"x":3792,"y":1273},{"x":3797,"y":1393},{"x":3521,"y":1405}],"normalizedVertices":[]},"paragraphs":[{"confidence":0.9728249311447144,"boundingBox":{"vertices":[{"x":3516,"y":1285},{"x":3792,"y":1273},{"x":3797,"y":1393},{"x":3521,"y":1405}],"normalizedVertices":[]},"words":[{"text":"7-08-2011","confidence":0.9884223341941833,"boundingBox":{"vertices":[{"x":3516,"y":1289},{"x":3791,"y":1273},{"x":3793,"y":1316},{"x":3518,"y":1332}],"normalizedVertices":[]}},{"text":"11-134","confidence":0.9494288563728333,"boundingBox":{"vertices":[{"x":3541,"y":1360},{"x":3696,"y":1355},{"x":3697,"y":1397},{"x":3542,"y":1402}],"normalizedVertices":[]}}]}]}]}]}